README.md
setup.cfg
setup.py
cassandra_backups/__init__.py
cassandra_backups/agent.py
cassandra_backups/logging_helper.py
cassandra_backups/main.py
cassandra_backups/snapshotting.py
cassandra_backups/timeout.py
cassandra_backups/utils.py
cassandra_backups_ek.egg-info/PKG-INFO
cassandra_backups_ek.egg-info/SOURCES.txt
cassandra_backups_ek.egg-info/dependency_links.txt
cassandra_backups_ek.egg-info/entry_points.txt
cassandra_backups_ek.egg-info/not-zip-safe
cassandra_backups_ek.egg-info/requires.txt
cassandra_backups_ek.egg-info/top_level.txt